{
  "project_info": {
    "project_number": "552498393629",
    "project_id": "quiz-app-4b8b4",
    "storage_bucket": "quiz-app-4b8b4.appspot.com"
  },
  "client": [
    {
      "client_info": {
        "mobilesdk_app_id": "1:552498393629:android:a89a43be562d4dd1344cf4",
        "android_client_info": {
          "package_name": "com.example.quizapp"
        }
      },
      "oauth_client": [
        {
          "client_id": "552498393629-s1uok6cf0drpsl13be4v3n0eifr7hl16.apps.googleusercontent.com",
          "client_type": 3
        }
      ],
      "api_key": [
        {
          "current_key": "AIzaSyD-948vgB501ZpKH0IAyQ3i4LMMLXSpygY"
        }
      ],
      "services": {
        "appinvite_service": {
          "other_platform_oauth_client": [
            {
              "client_id": "552498393629-s1uok6cf0drpsl13be4v3n0eifr7hl16.apps.googleusercontent.com",
              "client_type": 3
            }
          ]
        }
      }
    }
  ],
  "configuration_version": "1"
}